aquanta/__init__.py
aquanta/aquanta.py
aquanta-0.2.dist-info/COPYING
aquanta-0.2.dist-info/METADATA
aquanta-0.2.dist-info/WHEEL
aquanta-0.2.dist-info/top_level.txt
aquanta-0.2.dist-info/RECORD
