Metadata-Version: 2.1
Name: aquanta
Version: 0.2
Summary: Unofficial library to interact with Aquanta water heater smart controller.
Home-page: https://github.com/jeremy-compostella/aquanta
Author: Jeremy Compostella
Author-email: jeremy.compostella@gmail.com
Classifier: Programming Language :: Python :: 3
Classifier: License :: OSI Approved :: BSD License
Classifier: Operating System :: OS Independent
Classifier: Topic :: Home Automation
Requires-Python: >=3.6
License-File: COPYING
Requires-Dist: requests
